quickemail.py
quickemail-0.4.0.dist-info/LICENSE
quickemail-0.4.0.dist-info/METADATA
quickemail-0.4.0.dist-info/WHEEL
quickemail-0.4.0.dist-info/top_level.txt
quickemail-0.4.0.dist-info/RECORD
