Metadata-Version: 2.1
Name: quickemail
Version: 0.4.0
Summary: Quick send email use python3.
Home-page: http://clayboy.cn
Author: Clayboy
Author-email: clayboy@foxmail.com
License: UNKNOWN
Platform: UNKNOWN
License-File: LICENSE
